BrowserTray/__init__.py
BrowserTray/__main__.py
BrowserTray/chromium.png
BrowserTray/cmdline_args.py
BrowserTray/tray.py
BrowserTray/BrowserRepl/__init__.py
BrowserTray/ibrowser/__init__.py
BrowserTray/ibrowser/__main__.py
BrowserTray/ibrowser/repl.py
robotframework_browser_tray-1.8.2.dist-info/entry_points.txt
robotframework_browser_tray-1.8.2.dist-info/licenses/LICENSE
robotframework_browser_tray-1.8.2.dist-info/WHEEL
robotframework_browser_tray-1.8.2.dist-info/METADATA
robotframework_browser_tray-1.8.2.dist-info/RECORD
