Metadata-Version: 2.4
Name: robotframework-browser-tray
Version: 1.8.2
Summary: Tray icon and REPL for trying out Browser Library keywords using Chromium or Edge
Author-email: Marduk Bolaños <marduk.bolanos@imbus.de>
Requires-Python: >=3.9.0
License-File: LICENSE
Requires-Dist: pystray~=0.19.5
Requires-Dist: robotframework-browser>=18
Requires-Dist: robotframework-debug~=4.5.0
Project-URL: homepage, https://github.com/mardukbp/robotframework-browser-tray
